yaml_editor/__init__.py
yaml_editor/app.py
yaml_editor/cli.py
yaml_editor/templates/index.html
yaml_editor-0.1.8.dist-info/METADATA
yaml_editor-0.1.8.dist-info/WHEEL
yaml_editor-0.1.8.dist-info/entry_points.txt
yaml_editor-0.1.8.dist-info/RECORD
