Metadata-Version: 2.3
Name: yaml-editor
Version: 0.1.8
Summary: A web-based YAML editor with tabular interface
Author: Alfred Francis
Author-email: alfredfranciz@gmail.com
Requires-Python: >=3.7,<4.0
Classifier: Programming Language :: Python :: 3
Classifier: Programming Language :: Python :: 3.7
Classifier: Programming Language :: Python :: 3.8
Classifier: Programming Language :: Python :: 3.9
Classifier: Programming Language :: Python :: 3.10
Classifier: Programming Language :: Python :: 3.11
Classifier: Programming Language :: Python :: 3.12
Classifier: Programming Language :: Python :: 3.13
Requires-Dist: fastapi (>=0.95.0,<0.96.0)
Requires-Dist: jinja2 (>=3.1.2,<4.0.0)
Requires-Dist: pydantic (>=1.10.7,<2.0.0)
Requires-Dist: pyyaml (>=6.0,<7.0)
Requires-Dist: uvicorn (>=0.21.0,<0.22.0)
